{
  "schema": "eletypes-kbd/1",
  "meta": {
    "name": "Generic 75% ANSI",
    "author": "eletypes",
    "version": "1.0",
    "description": "Standard 75% ANSI layout"
  },
  "board": {
    "id": "generic-75-ansi",
    "formFactor": "75%",
    "layoutStagger": "row-staggered",
    "standard": "ANSI",
    "width": 16.5,
    "height": 6.25,
    "keyboardType": "mechanical"
  },
  "layout": {
    "keys": [
      { "id": "Escape", "keyName": "Escape", "label": "Esc", "x": 0, "y": 0, "w": 1, "kind": "accent", "cluster": "fn-row" },
      { "id": "F1",     "keyName": "F1",     "label": "F1",  "x": 1.5, "y": 0, "w": 1, "kind": "fn", "cluster": "fn-row" },
      { "id": "KeyA",   "keyName": "KeyA",   "label": "A",   "x": 1.75, "y": 3.25, "w": 1, "cluster": "alpha" },
      { "id": "KeyF",   "keyName": "KeyF",   "label": "F",   "x": 4.75, "y": 3.25, "w": 1, "cluster": "alpha", "capRef": "cherry-homing" },
      { "id": "Space",  "keyName": "Space",  "label": "",    "x": 3.75, "y": 5.25, "w": 6.25, "kind": "accent", "cluster": "bottom-row" },
      { "id": "Escape-artisan", "keyName": "Escape", "label": "Esc", "x": 0, "y": 0, "w": 1, "kind": "accent", "capRef": "dragon-artisan" }
    ]
  }
}
